umcn_consent/__init__.py
umcn_consent/auth.py
umcn_consent/core.py
umcn_consent-1.1.1.dist-info/LICENSE
umcn_consent-1.1.1.dist-info/METADATA
umcn_consent-1.1.1.dist-info/WHEEL
umcn_consent-1.1.1.dist-info/RECORD
